{"trial_id": "15", "hyperparameters": {"space": [{"class_name": "Int", "config": {"name": "num_layers", "default": null, "conditions": [], "min_value": 1, "max_value": 2, "step": 1, "sampling": "linear"}}, {"class_name": "Choice", "config": {"name": "units_0", "default": 32, "conditions": [], "values": [32, 64, 128], "ordered": true}}, {"class_name": "Choice", "config": {"name": "dropout_0", "default": 0.1, "conditions": [], "values": [0.1, 0.2, 0.3], "ordered": true}}, {"class_name": "Choice", "config": {"name": "learning_rate", "default": 0.001, "conditions": [], "values": [0.001, 0.0005, 0.0001], "ordered": true}}, {"class_name": "Choice", "config": {"name": "units_1", "default": 32, "conditions": [], "values": [32, 64, 128], "ordered": true}}, {"class_name": "Choice", "config": {"name": "dropout_1", "default": 0.1, "conditions": [], "values": [0.1, 0.2, 0.3], "ordered": true}}], "values": {"num_layers": 2, "units_0": 64, "dropout_0": 0.3, "learning_rate": 0.0001, "units_1": 128, "dropout_1": 0.3}}, "metrics": {"metrics": {"loss": {"direction": "min", "observations": [{"value": [0.5419619083404541], "step": 25}]}, "val_loss": {"direction": "min", "observations": [{"value": [0.2744276225566864], "step": 25}]}}}, "score": 0.2744276225566864, "best_step": 25, "status": "COMPLETED", "message": null}